datadis/__init__.py
datadis/types.py
datadis-1.0.1.dist-info/LICENSE
datadis-1.0.1.dist-info/METADATA
datadis-1.0.1.dist-info/WHEEL
datadis-1.0.1.dist-info/RECORD
