Metadata-Version: 2.1
Name: datadis
Version: 1.0.1
Summary: Datadis API client
Author: Alvaro Tinoco
Author-email: alvarotinocomarmol@gmail.com
Requires-Python: >=3.8,<4.0
Classifier: Programming Language :: Python :: 3
Classifier: Programming Language :: Python :: 3.8
Classifier: Programming Language :: Python :: 3.9
Classifier: Programming Language :: Python :: 3.10
Classifier: Programming Language :: Python :: 3.11
Classifier: Programming Language :: Python :: 3.12
Requires-Dist: httpx (>=0.19,<0.24)
